openapi_client/LICENSE
openapi_client/__init__.py
openapi_client/api_client.py
openapi_client/configuration.py
openapi_client/exceptions.py
openapi_client/rest.py
openapi_client/aio/__init__.py
openapi_client/aio/api_client.py
openapi_client/aio/configuration.py
openapi_client/aio/exceptions.py
openapi_client/aio/rest.py
openapi_client/aio/api/__init__.py
openapi_client/aio/models/__init__.py
openapi_client/api/__init__.py
openapi_client/api/auth_api.py
openapi_client/api/contracts_api.py
openapi_client/api/files_api.py
openapi_client/api/inpy_versions_api.py
openapi_client/api/organisations_api.py
openapi_client/api/permissions_api.py
openapi_client/api/repositories_api.py
openapi_client/api/revisions_api.py
openapi_client/api/roles_api.py
openapi_client/api/simulations_api.py
openapi_client/api/statuses_api.py
openapi_client/api/threedimodels_api.py
openapi_client/api/usage_api.py
openapi_client/models/__init__.py
openapi_client/models/action.py
openapi_client/models/aggregation_settings.py
openapi_client/models/arrival_time_post_processing.py
openapi_client/models/authenticate.py
openapi_client/models/base_event_state.py
openapi_client/models/basic_post_processing.py
openapi_client/models/boundary_condition.py
openapi_client/models/breach.py
openapi_client/models/breach_graph.py
openapi_client/models/breach_graph_request.py
openapi_client/models/constant_lateral.py
openapi_client/models/constant_leakage.py
openapi_client/models/constant_local_rain.py
openapi_client/models/constant_rain.py
openapi_client/models/constant_sources_sinks.py
openapi_client/models/constant_wind.py
openapi_client/models/contract.py
openapi_client/models/current_status.py
openapi_client/models/damage_estimation.py
openapi_client/models/damage_post_processing.py
openapi_client/models/download.py
openapi_client/models/event.py
openapi_client/models/extent.py
openapi_client/models/file.py
openapi_client/models/file_boundary_condition.py
openapi_client/models/file_lateral.py
threedi_api_client-4.2.4.dist-info/licenses/AUTHORS.rst
threedi_api_client-4.2.4.dist-info/licenses/LICENSE
threedi_api_client-4.2.4.dist-info/METADATA
threedi_api_client-4.2.4.dist-info/WHEEL
threedi_api_client-4.2.4.dist-info/top_level.txt
threedi_api_client-4.2.4.dist-info/RECORD
