Metadata-Version: 2.4
Name: threedi-api-client
Version: 4.2.4
Summary: client for the threedi API
Home-page: https://github.com/nens/threedi-api-client
Author: Lars Claussen
Author-email: lars.claussen@nelen-schuurmans.nl
License: BSD license
Keywords: threedi-api-client
Classifier: Development Status :: 4 - Beta
Classifier: Intended Audience :: Developers
Classifier: License :: OSI Approved :: BSD License
Classifier: Natural Language :: English
Classifier: Programming Language :: Python :: 3
Requires-Python: >=3.7
License-File: LICENSE
License-File: AUTHORS.rst
Requires-Dist: certifi>=2019.3.9
Requires-Dist: urllib3<3.0.0,>=2.0
Requires-Dist: six>=1.10
Requires-Dist: python-dateutil
Provides-Extra: aio
Requires-Dist: aiohttp<3.10,>=3.6.3; extra == "aio"
Requires-Dist: aiofiles>=0.6; extra == "aio"
Provides-Extra: test
Requires-Dist: pytest; extra == "test"
Requires-Dist: pytest-asyncio; extra == "test"
Requires-Dist: mock; python_version < "3.8" and extra == "test"
Requires-Dist: pyjwt; extra == "test"
Provides-Extra: docs
Requires-Dist: sphinx-rtd-theme; extra == "docs"
Dynamic: author
Dynamic: author-email
Dynamic: classifier
Dynamic: description
Dynamic: home-page
Dynamic: keywords
Dynamic: license
Dynamic: license-file
Dynamic: provides-extra
Dynamic: requires-dist
Dynamic: requires-python
Dynamic: summary
